odoo/addons/pos_product_expiry/README.rst
odoo/addons/pos_product_expiry/__init__.py
odoo/addons/pos_product_expiry/__manifest__.py
odoo/addons/pos_product_expiry/i18n/es.po
odoo/addons/pos_product_expiry/i18n/fr.po
odoo/addons/pos_product_expiry/i18n/it.po
odoo/addons/pos_product_expiry/i18n/pos_product_expiry.pot
odoo/addons/pos_product_expiry/models/__init__.py
odoo/addons/pos_product_expiry/models/pos_config.py
odoo/addons/pos_product_expiry/models/pos_session.py
odoo/addons/pos_product_expiry/models/res_config_settings.py
odoo/addons/pos_product_expiry/models/stock_lot.py
odoo/addons/pos_product_expiry/readme/CONTRIBUTORS.md
odoo/addons/pos_product_expiry/readme/DESCRIPTION.md
odoo/addons/pos_product_expiry/static/description/icon.png
odoo/addons/pos_product_expiry/static/description/index.html
odoo/addons/pos_product_expiry/static/src/js/app/models.esm.js
odoo/addons/pos_product_expiry/static/tests/tours/ProductExpiry.tour.esm.js
odoo/addons/pos_product_expiry/tests/__init__.py
odoo/addons/pos_product_expiry/tests/test_frontend.py
odoo/addons/pos_product_expiry/views/res_config_settings_views.xml
odoo_addon_pos_product_expiry-17.0.1.0.1.dist-info/METADATA
odoo_addon_pos_product_expiry-17.0.1.0.1.dist-info/WHEEL
odoo_addon_pos_product_expiry-17.0.1.0.1.dist-info/top_level.txt
odoo_addon_pos_product_expiry-17.0.1.0.1.dist-info/RECORD
