Metadata-Version: 2.1
Name: odoo-addon-pos_product_expiry
Version: 17.0.1.0.1
Requires-Python: >=3.10
Requires-Dist: odoo-addon-pos_lot_selection>=17.0dev,<17.1dev
Requires-Dist: odoo>=17.0a,<17.1dev
Summary: Evaluate expiry of lot
Home-page: https://github.com/OCA/pos
License: AGPL-3
Author: Dixmit,INVITU,Odoo Community Association (OCA)
Author-email: support@odoo-community.org
Classifier: Programming Language :: Python
Classifier: Framework :: Odoo
Classifier: Framework :: Odoo :: 17.0
Classifier: License :: OSI Approved :: GNU Affero General Public License v3
